streamlit_clickable_images/__init__.py
streamlit_clickable_images/example.py
streamlit_clickable_images/frontend/build/asset-manifest.json
streamlit_clickable_images/frontend/build/bootstrap.min.css
streamlit_clickable_images/frontend/build/index.html
streamlit_clickable_images/frontend/build/static/js/main.5ac59a49.js
streamlit_clickable_images/frontend/build/static/js/main.5ac59a49.js.LICENSE.txt
streamlit_clickable_images/frontend/build/static/js/main.5ac59a49.js.map
streamlit_clickable_images/frontend/build/static/js/main.ef23b9d0.js
streamlit_clickable_images/frontend/build/static/js/main.ef23b9d0.js.LICENSE.txt
streamlit_clickable_images/frontend/build/static/js/main.ef23b9d0.js.map
streamlit_clickable_images/frontend/build/static/js/main.f8ef253f.js
streamlit_clickable_images/frontend/build/static/js/main.f8ef253f.js.LICENSE.txt
streamlit_clickable_images/frontend/build/static/js/main.f8ef253f.js.map
streamlit_clickable_images-0.0.3.dist-info/LICENSE
streamlit_clickable_images-0.0.3.dist-info/METADATA
streamlit_clickable_images-0.0.3.dist-info/WHEEL
streamlit_clickable_images-0.0.3.dist-info/top_level.txt
streamlit_clickable_images-0.0.3.dist-info/RECORD
